attrdict/__init__.py
attrdict-1.0.0.dist-info/DESCRIPTION.rst
attrdict-1.0.0.dist-info/METADATA
attrdict-1.0.0.dist-info/metadata.json
attrdict-1.0.0.dist-info/RECORD
attrdict-1.0.0.dist-info/top_level.txt
attrdict-1.0.0.dist-info/WHEEL
